<?xml version="1.0" encoding="UTF-8"?>
<!DOCTYPE configuration
  PUBLIC "-//mybatis.org//DTD Config 3.0//EN"
  "http://mybatis.org/dtd/mybatis-3-config.dtd">
<configuration>
  <typeAliases>
    <typeAlias alias="memberVo"  type="net.koreate.vo.MemberVo"/>
    <typeAlias alias="freeBoardVo"  type="net.koreate.vo.FreeBoardVo"/>
    <typeAlias alias="commentVo"  type="net.koreate.vo.CommentVo"/>
    
  </typeAliases>

<mappers>
<mapper resource="sql/memberMapper.xml"/>
<mapper resource="sql/boardfMapper.xml"/>
<mapper resource="sql/commentMapper.xml"/>


</mappers>
    
    
    
  
  </configuration>
  